models/__init__.py
models/client.py
models/connection.py
utils/__init__.py
utils/helpers.py
PingTool-1.2.5.dist-info/LICENSE
PingTool-1.2.5.dist-info/METADATA
PingTool-1.2.5.dist-info/WHEEL
PingTool-1.2.5.dist-info/top_level.txt
PingTool-1.2.5.dist-info/zip-safe
PingTool-1.2.5.dist-info/RECORD
