Metadata-Version: 2.1
Name: PingTool
Version: 1.2.5
Summary: Small application written in Python, socket-based. to ping annoying colleague's who won't respond.
Home-page: https://github.com/DeadlyFirex/PingTool
Author: deadly
Author-email: 
License: MIT
Project-URL: Bug Tracker, https://github.com/DeadlyFirex/PingTool/issues
Platform: any
Classifier: Programming Language :: Python :: 3.10
Classifier: Programming Language :: Python :: 3.11
Classifier: License :: OSI Approved :: MIT License
Classifier: Operating System :: OS Independent
Classifier: Natural Language :: English
Classifier: Topic :: Utilities
Requires-Python: >=3.10
License-File: LICENSE
Requires-Dist: loguru >=0.7.0
Requires-Dist: setuptools >=69.0.3
